LICENSE
README.md
setup.cfg
setup.py
autostr/__init__.py
autostr/_autostr_index.py
autostr.egg-info/PKG-INFO
autostr.egg-info/SOURCES.txt
autostr.egg-info/dependency_links.txt
autostr.egg-info/top_level.txt