Metadata-Version: 2.1
Name: autostr
Version: 1.7
Home-page: https://github.com/number3141/autostr
Author: Andrey Kuchebo
Author-email: kucheboandrey@gmail.com
License-File: LICENSE
